salesforcecdpconnector/__init__.py
salesforcecdpconnector/authentication_helper.py
salesforcecdpconnector/connection.py
salesforcecdpconnector/constants.py
salesforcecdpconnector/cursor.py
salesforcecdpconnector/exceptions.py
salesforcecdpconnector/genie_table.py
salesforcecdpconnector/metadata_processor.py
salesforcecdpconnector/pandas_utils.py
salesforcecdpconnector/parsed_query_result.py
salesforcecdpconnector/query_result_parser.py
salesforcecdpconnector/query_submitter.py
salesforce_cdp_connector-1.0.16.dist-info/METADATA
salesforce_cdp_connector-1.0.16.dist-info/WHEEL
salesforce_cdp_connector-1.0.16.dist-info/licenses/LICENSE.txt
salesforce_cdp_connector-1.0.16.dist-info/RECORD
