Metadata-Version: 2.4
Name: salesforce-cdp-connector
Version: 1.0.16
Summary: Salesforce Data Cloud Python Connector
Project-URL: homepage, https://github.com/forcedotcom/salesforce-cdp-connector
Project-URL: source, https://github.com/forcedotcom/salesforce-cdp-connector
Author-email: Data Cloud Query Developer Team <datacloud-query-connector-owners@salesforce.com>
License-Expression: BSD-3-Clause
License-File: LICENSE.txt
Keywords: cdp,dbapi,salesforce
Requires-Python: >=3.8
Requires-Dist: pandas>=2.0.3
Requires-Dist: pyarrow>=17.0.0
Requires-Dist: pyjwt>=2.9.0
Requires-Dist: python-dateutil>=2.9.0.post0
Requires-Dist: requests>=2.32.3
Requires-Dist: urllib3>=2.2.3
